recogito/__init__.py
recogito/admin.py
recogito/api_renderers.py
recogito/api_serializers.py
recogito/api_views.py
recogito/apps.py
recogito/models.py
recogito/tests.py
recogito/views.py
django_recogito-0.1.0.dist-info/METADATA
django_recogito-0.1.0.dist-info/WHEEL
django_recogito-0.1.0.dist-info/top_level.txt
django_recogito-0.1.0.dist-info/RECORD
